canals/__about__.py
canals/__init__.py
canals/errors.py
canals/serialization.py
canals/type_utils.py
canals/component/__init__.py
canals/component/component.py
canals/component/connection.py
canals/component/descriptions.py
canals/component/sockets.py
canals/component/types.py
canals/pipeline/__init__.py
canals/pipeline/descriptions.py
canals/pipeline/pipeline.py
canals/pipeline/validation.py
canals/pipeline/draw/__init__.py
canals/pipeline/draw/draw.py
canals/pipeline/draw/graphviz.py
canals/pipeline/draw/mermaid.py
canals/testing/__init__.py
canals/testing/factory.py
canals-0.11.0.dist-info/METADATA
canals-0.11.0.dist-info/WHEEL
canals-0.11.0.dist-info/licenses/LICENSE
canals-0.11.0.dist-info/RECORD
